SerialHelpers/__init__.py
SerialHelpers/helpers.c
SerialHelpers/helpers.cp312-win_amd64.pyd
serialhelperslib-0.4.2.dist-info/METADATA
serialhelperslib-0.4.2.dist-info/WHEEL
serialhelperslib-0.4.2.dist-info/top_level.txt
serialhelperslib-0.4.2.dist-info/RECORD
